setup.py
test_mana.py
mana/__init__.py
mana/mana.py
mana.egg-info/PKG-INFO
mana.egg-info/SOURCES.txt
mana.egg-info/dependency_links.txt
mana.egg-info/entry_points.txt
mana.egg-info/not-zip-safe
mana.egg-info/requires.txt
mana.egg-info/top_level.txt
mana/operators/__init__.py
mana/operators/_mkdir_p.py
mana/operators/init_code.py
mana/templates/__init__.py
mana/templates/admin/__init__.py
mana/templates/admin/_admin_index_html.py
mana/templates/admin/_admin_logout_html.py
mana/templates/admin/_admin_views.py
mana/templates/auth/__init__.py
mana/templates/auth/_auth_forms.py
mana/templates/auth/_auth_login_css.py
mana/templates/auth/_auth_login_html.py
mana/templates/auth/_auth_views.py
mana/templates/config/__init__.py
mana/templates/config/_config_code.py
mana/templates/forms/__init__.py
mana/templates/forms/forms.py
mana/templates/help/__init__.py
mana/templates/init/__init__.py
mana/templates/init/_init_admin.py
mana/templates/init/_init_basic.py
mana/templates/init/_init_blueprint.py
mana/templates/manage/__init__.py
mana/templates/manage/_manage_admin.py
mana/templates/manage/_manage_basic.py
mana/templates/models/__init__.py
mana/templates/models/_models_admin.py
mana/templates/models/_models_code.py
mana/templates/requirement/__init__.py
mana/templates/requirement/_requirement_admin.py
mana/templates/requirement/_requirement_code.py
mana/templates/views/__init__.py
mana/templates/views/_views_basic.py
mana/templates/views/_views_blueprint.py